{
  "$schema": "https://shadcn-svelte.com/schema/registry.json",
  "name": "ndk-svelte",
  "homepage": "https://ndk.fyi",
  "aliases": {
    "lib": "$lib",
    "ndk": "@nostr-dev-kit/ndk",
    "ndk-svelte": "@nostr-dev-kit/svelte",
    "builders": "$lib/builders",
    "ui": "$lib/ui",
    "utils": "$lib/utils"
  },
  "items": [
    {
      "name": "article-card-medium",
      "type": "registry:component",
      "title": "Article Card Medium",
      "description": "Block component - article card medium",
      "registryDependencies": [],
      "dependencies": [
        "@nostr-dev-kit/ndk",
        "@nostr-dev-kit/svelte"
      ],
      "files": [
        {
          "path": "registry/ndk/components/article-card/article-card-medium.svelte",
          "type": "registry:ui"
        }
      ],
      "version": "0.0.0",
      "updatedAt": "2025-11-06T13:43:00.174Z"
    },
    {
      "name": "article-content",
      "type": "registry:component",
      "title": "Article Content",
      "description": "Render NIP-23 article content with markdown support, inline highlights, text selection, and floating avatars",
      "registryDependencies": [],
      "dependencies": [
        "@nostr-dev-kit/ndk",
        "@nostr-dev-kit/svelte",
        "marked@^16.4.1"
      ],
      "files": [
        {
          "path": "registry/ndk/article-content/article-content.svelte",
          "type": "registry:ui"
        },
        {
          "path": "registry/ndk/article-content/highlight-toolbar.svelte",
          "type": "registry:ui"
        },
        {
          "path": "registry/ndk/article-content/index.ts",
          "type": "registry:lib"
        }
      ],
      "version": "0.4.0",
      "updatedAt": "2025-10-31T07:15:56.000Z"
    },
    {
      "name": "avatar-group",
      "type": "registry:component",
      "title": "Avatar Group",
      "description": "Display multiple user avatars in a stacked group with smart ordering",
      "registryDependencies": [
        "user-profile"
      ],
      "dependencies": [
        "@nostr-dev-kit/ndk",
        "@nostr-dev-kit/svelte"
      ],
      "files": [
        {
          "path": "registry/ndk/avatar-group/avatar-group.svelte",
          "type": "registry:component"
        },
        {
          "path": "registry/ndk/avatar-group/index.ts",
          "type": "registry:lib"
        }
      ],
      "version": "0.4.0",
      "updatedAt": "2025-10-31T07:15:56.000Z"
    },
    {
      "name": "emoji-picker",
      "type": "registry:block",
      "title": "Emoji Picker",
      "description": "Flexible emoji selection components with support for user's custom emojis from Nostr (NIP-51 kind:10030) and aggregated emojis from specified pubkeys",
      "registryDependencies": [],
      "dependencies": [
        "@nostr-dev-kit/ndk",
        "@nostr-dev-kit/svelte",
        "bits-ui@^2.8.3"
      ],
      "files": [
        {
          "path": "registry/ndk/emoji-picker/emoji-picker-list.svelte",
          "type": "registry:component"
        },
        {
          "path": "registry/ndk/emoji-picker/emoji-picker-content.svelte",
          "type": "registry:component"
        },
        {
          "path": "registry/ndk/emoji-picker/index.ts",
          "type": "registry:lib"
        }
      ],
      "version": "0.3.0",
      "updatedAt": "2025-10-31T07:15:56.000Z"
    },
    {
      "name": "event-card",
      "type": "registry:component",
      "title": "Event Card",
      "description": "Composable event card components with Context API - mix and match Root, Header, Content, Actions",
      "registryDependencies": [
        "user-profile",
        "event-content",
        "actions",
        "ndk-context"
      ],
      "dependencies": [
        "@nostr-dev-kit/ndk",
        "@nostr-dev-kit/svelte"
      ],
      "files": [
        {
          "path": "registry/ndk/components/event-card/event-card.context.ts",
          "type": "registry:lib"
        },
        {
          "path": "registry/ndk/components/event-card/event-card-root.svelte",
          "type": "registry:component"
        },
        {
          "path": "registry/ndk/components/event-card/event-card-header.svelte",
          "type": "registry:component"
        },
        {
          "path": "registry/ndk/components/event-card/event-card-content.svelte",
          "type": "registry:component"
        },
        {
          "path": "registry/ndk/components/event-card/event-card-actions.svelte",
          "type": "registry:component"
        },
        {
          "path": "registry/ndk/components/event-card/event-card-dropdown.svelte",
          "type": "registry:component"
        },
        {
          "path": "registry/ndk/components/event-card/index.ts",
          "type": "registry:lib"
        }
      ],
      "version": "0.0.0",
      "updatedAt": "2025-11-06T13:43:01.234Z"
    },
    {
      "name": "follow-pack-list-item",
      "type": "registry:component",
      "title": "Follow Pack List Item",
      "description": "Follow button component - follow pack list item variant",
      "registryDependencies": [],
      "dependencies": [
        "@nostr-dev-kit/ndk",
        "@nostr-dev-kit/svelte"
      ],
      "files": [
        {
          "path": "registry/ndk/components/follow-pack/follow-pack-list-item.svelte",
          "type": "registry:ui"
        }
      ],
      "version": "0.0.0",
      "updatedAt": "2025-11-06T13:43:01.387Z"
    },
    {
      "name": "highlight-card-elegant",
      "type": "registry:component",
      "title": "Highlight Card Elegant",
      "description": "Block component - highlight card elegant",
      "registryDependencies": [],
      "dependencies": [
        "@nostr-dev-kit/ndk",
        "@nostr-dev-kit/svelte"
      ],
      "files": [
        {
          "path": "registry/ndk/components/highlight-card/highlight-card-elegant.svelte",
          "type": "registry:ui"
        }
      ],
      "version": "0.0.0",
      "updatedAt": "2025-11-06T13:43:01.543Z"
    },
    {
      "name": "highlight-card-feed",
      "type": "registry:component",
      "title": "Highlight Card Feed",
      "description": "Block component - highlight card feed",
      "registryDependencies": [],
      "dependencies": [
        "@nostr-dev-kit/ndk",
        "@nostr-dev-kit/svelte"
      ],
      "files": [
        {
          "path": "registry/ndk/components/highlight-card/highlight-card-feed.svelte",
          "type": "registry:ui"
        }
      ],
      "version": "0.0.0",
      "updatedAt": "2025-11-06T13:43:01.695Z"
    },
    {
      "name": "highlight-card-grid",
      "type": "registry:component",
      "title": "Highlight Card Grid",
      "description": "Block component - highlight card grid",
      "registryDependencies": [],
      "dependencies": [
        "@nostr-dev-kit/ndk",
        "@nostr-dev-kit/svelte"
      ],
      "files": [
        {
          "path": "registry/ndk/components/highlight-card/highlight-card-grid.svelte",
          "type": "registry:ui"
        }
      ],
      "version": "0.0.0",
      "updatedAt": "2025-11-06T13:43:01.851Z"
    },
    {
      "name": "image-card",
      "type": "registry:component",
      "title": "Image Card",
      "description": "Block component - image card",
      "registryDependencies": [],
      "dependencies": [
        "@nostr-dev-kit/ndk",
        "@nostr-dev-kit/svelte"
      ],
      "files": [
        {
          "path": "registry/ndk/components/image-card/image-card.svelte",
          "type": "registry:ui"
        }
      ],
      "version": "0.0.0",
      "updatedAt": "2025-11-06T13:43:02.009Z"
    },
    {
      "name": "image-card-instagram",
      "type": "registry:component",
      "title": "Image Card Instagram",
      "description": "Block component - image card instagram",
      "registryDependencies": [],
      "dependencies": [
        "@nostr-dev-kit/ndk",
        "@nostr-dev-kit/svelte"
      ],
      "files": [
        {
          "path": "registry/ndk/components/image-card/image-card-instagram.svelte",
          "type": "registry:ui"
        }
      ],
      "version": "0.0.0",
      "updatedAt": "2025-11-06T13:43:02.159Z"
    },
    {
      "name": "relay-card",
      "type": "registry:component",
      "title": "Relay Card",
      "description": "Display relay information and status",
      "registryDependencies": [],
      "dependencies": [
        "@nostr-dev-kit/ndk",
        "@nostr-dev-kit/svelte"
      ],
      "files": [
        {
          "path": "registry/ndk/relay-card/relay-card.svelte",
          "type": "registry:ui"
        }
      ],
      "version": "0.8.0",
      "updatedAt": "2025-10-31T07:15:56.000Z"
    },
    {
      "name": "user-input",
      "type": "registry:block",
      "title": "User Input",
      "description": "Composable user search and selection components - search cached profiles, supports NIP-05/npub/nprofile lookups",
      "registryDependencies": [],
      "dependencies": [
        "@nostr-dev-kit/ndk",
        "@nostr-dev-kit/svelte"
      ],
      "files": [
        {
          "path": "registry/ndk/ui/user-input/user-input.context.ts",
          "type": "registry:lib"
        },
        {
          "path": "registry/ndk/ui/user-input/user-input-root.svelte",
          "type": "registry:component"
        },
        {
          "path": "registry/ndk/ui/user-input/user-input-search.svelte",
          "type": "registry:component"
        },
        {
          "path": "registry/ndk/ui/user-input/user-input-results.svelte",
          "type": "registry:component"
        },
        {
          "path": "registry/ndk/ui/user-input/user-input-item.svelte",
          "type": "registry:component"
        },
        {
          "path": "registry/ndk/ui/user-input/index.ts",
          "type": "registry:lib"
        }
      ],
      "version": "0.0.0",
      "updatedAt": "2025-11-06T13:43:02.690Z"
    },
    {
      "name": "user-profile-hero",
      "type": "registry:component",
      "title": "User Profile Hero",
      "description": "Block component - user profile hero",
      "registryDependencies": [],
      "dependencies": [
        "@nostr-dev-kit/ndk",
        "@nostr-dev-kit/svelte"
      ],
      "files": [
        {
          "path": "registry/ndk/components/user-profile-hero/user-profile-hero.svelte",
          "type": "registry:ui"
        }
      ],
      "version": "0.0.0",
      "updatedAt": "2025-11-06T13:43:02.844Z"
    },
    {
      "name": "voice-message-card-compact",
      "type": "registry:component",
      "title": "Voice Message Card Compact",
      "description": "Block component - voice message card compact",
      "registryDependencies": [],
      "dependencies": [
        "@nostr-dev-kit/ndk",
        "@nostr-dev-kit/svelte"
      ],
      "files": [
        {
          "path": "registry/ndk/components/voice-message-card-compact/voice-message-card-compact.svelte",
          "type": "registry:ui"
        }
      ],
      "version": "0.0.0",
      "updatedAt": "2025-11-06T13:43:02.995Z"
    },
    {
      "name": "voice-message-card-expanded",
      "type": "registry:component",
      "title": "Voice Message Card Expanded",
      "description": "Block component - voice message card expanded",
      "registryDependencies": [],
      "dependencies": [
        "@nostr-dev-kit/ndk",
        "@nostr-dev-kit/svelte"
      ],
      "files": [
        {
          "path": "registry/ndk/components/voice-message-card-expanded/voice-message-card-expanded.svelte",
          "type": "registry:ui"
        }
      ],
      "version": "0.0.0",
      "updatedAt": "2025-11-06T13:43:03.143Z"
    },
    {
      "name": "zap-button",
      "type": "registry:component",
      "title": "Zap Button",
      "description": "Lightning payment button with amount selector",
      "registryDependencies": [],
      "dependencies": [
        "@nostr-dev-kit/ndk",
        "@nostr-dev-kit/svelte",
        "@nostr-dev-kit/wallet"
      ],
      "files": [
        {
          "path": "registry/ndk/zap-button/zap-button.svelte",
          "type": "registry:ui"
        }
      ],
      "version": "0.0.0",
      "updatedAt": "2025-11-06T13:43:03.289Z"
    }
  ],
  "version": "4.0.0-beta.41"
}